<?xml version="1.0" encoding="utf-8"?>
<?xml-stylesheet type="text/xsl" href="ActivityLog.xsl"?>
<BuildInformation>
  <BuildInformationNode Id="0f43d437-d573-4d70-abd0-a597a361d63b" Type="ActivityTracking">
  <Fields>
    <InformationField Name="ActivityInstanceId" Value="1" />
    <InformationField Name="ActivityType" Value="DynamicActivity" />
    <InformationField Name="DisplayName" Value="Overall Build Process" />
    <InformationField Name="Duration" Value="00:01:42" />
    <InformationField Name="State" Value="Closed" />
    <InformationField Name="StartTime" Value="2014-05-26T14:21:37.2168174Z" />
    <InformationField Name="FinishTime" Value="2014-05-26T14:23:19.2947138Z" />
  </Fields>
<Children><BuildInformationNode Id="a8ca6f1f-785f-48c7-b346-97cf5e47f213" ParentId="0f43d437-d573-4d70-abd0-a597a361d63b" Type="ActivityTracking">
  <Fields>
    <InformationField Name="ActivityInstanceId" Value="3" />
    <InformationField Name="ActivityType" Value="GetBuildDetail" />
    <InformationField Name="DisplayName" Value="Get the Build" />
    <InformationField Name="Duration" Value="00:00:00" />
    <InformationField Name="State" Value="Closed" />
    <InformationField Name="StartTime" Value="2014-05-26T14:21:37.4212597Z" />
    <InformationField Name="FinishTime" Value="2014-05-26T14:21:37.4218172Z" />
  </Fields>
<Children /></BuildInformationNode><BuildInformationNode Id="84d0cec0-3977-4037-abf9-b5b92ef5fe3f" ParentId="0f43d437-d573-4d70-abd0-a597a361d63b" Type="ActivityTracking">
  <Fields>
    <InformationField Name="ActivityInstanceId" Value="4" />
    <InformationField Name="ActivityType" Value="Sequence" />
    <InformationField Name="DisplayName" Value="Update Drop Location" />
    <InformationField Name="Duration" Value="00:00:00" />
    <InformationField Name="State" Value="Closed" />
    <InformationField Name="StartTime" Value="2014-05-26T14:21:37.4368177Z" />
    <InformationField Name="FinishTime" Value="2014-05-26T14:21:37.9536341Z" />
  </Fields>
<Children><BuildInformationNode Id="278eeba0-0575-4e59-9096-755638e16a55" ParentId="84d0cec0-3977-4037-abf9-b5b92ef5fe3f" Type="ActivityTracking">
  <Fields>
    <InformationField Name="ActivityInstanceId" Value="11" />
    <InformationField Name="ActivityType" Value="UpdateBuildNumber" />
    <InformationField Name="DisplayName" Value="Update Build Number" />
    <InformationField Name="Duration" Value="00:00:00" />
    <InformationField Name="State" Value="Closed" />
    <InformationField Name="StartTime" Value="2014-05-26T14:21:37.4458179Z" />
    <InformationField Name="FinishTime" Value="2014-05-26T14:21:37.6408073Z" />
  </Fields>
<Children><BuildInformationNode Id="9e251440-b3c8-4fc2-999c-a6de847b8455" ParentId="278eeba0-0575-4e59-9096-755638e16a55" Type="ActivityInput">
  <Fields>
    <InformationField Name="BuildNumberFormat" Value="$(BuildDefinitionName)_$(Date:yyyyMMdd)$(Rev:.r)" />
  </Fields>
<Children /></BuildInformationNode><BuildInformationNode Id="95f6883b-1a43-435a-9258-7bcc38b54c20" ParentId="278eeba0-0575-4e59-9096-755638e16a55" Type="ActivityOutput">
  <Fields>
    <InformationField Name="Result" Value="tweetz5_20140526.1" />
  </Fields>
<Children /></BuildInformationNode></Children></BuildInformationNode><BuildInformationNode Id="a59b6605-419f-4cb4-943c-66ea1d88abdf" ParentId="84d0cec0-3977-4037-abf9-b5b92ef5fe3f" Type="ActivityTracking">
  <Fields>
    <InformationField Name="ActivityInstanceId" Value="12" />
    <InformationField Name="ActivityType" Value="If" />
    <InformationField Name="DisplayName" Value="If Build Reason is Triggered" />
    <InformationField Name="Duration" Value="00:00:00" />
    <InformationField Name="State" Value="Closed" />
    <InformationField Name="StartTime" Value="2014-05-26T14:21:37.6448188Z" />
    <InformationField Name="FinishTime" Value="2014-05-26T14:21:37.9506353Z" />
  </Fields>
<Children><BuildInformationNode Id="e27de0d2-3471-4928-aef3-be3ca1f710f7" ParentId="a59b6605-419f-4cb4-943c-66ea1d88abdf" Type="ActivityTracking">
  <Fields>
    <InformationField Name="ActivityInstanceId" Value="15" />
    <InformationField Name="ActivityType" Value="SetBuildProperties" />
    <InformationField Name="DisplayName" Value="Set Drop Location" />
    <InformationField Name="Duration" Value="00:00:00" />
    <InformationField Name="State" Value="Closed" />
    <InformationField Name="StartTime" Value="2014-05-26T14:21:37.8538380Z" />
    <InformationField Name="FinishTime" Value="2014-05-26T14:21:37.9496214Z" />
  </Fields>
<Children><BuildInformationNode Id="e3eb4c0d-719c-4ab6-a496-2051a6301e00" ParentId="e27de0d2-3471-4928-aef3-be3ca1f710f7" Type="ActivityInput">
  <Fields>
    <InformationField Name="LabelName" />
    <InformationField Name="SourceGetVersion" />
    <InformationField Name="KeepForever" Value="False" />
    <InformationField Name="DropLocation" Value="$/tweetz5/Drops/tweetz5/tweetz5_20140526.1" />
    <InformationField Name="Status" Value="None" />
    <InformationField Name="LogLocation" />
    <InformationField Name="BuildNumber" />
    <InformationField Name="Quality" />
    <InformationField Name="TestStatus" Value="Unknown" />
    <InformationField Name="CompilationStatus" Value="Unknown" />
  </Fields>
<Children /></BuildInformationNode></Children></BuildInformationNode><BuildInformationNode Id="4b96240e-934f-4950-91c4-e601a41cf7be" ParentId="a59b6605-419f-4cb4-943c-66ea1d88abdf" Type="ActivityInput">
  <Fields>
    <InformationField Name="Condition" Value="True" />
  </Fields>
<Children /></BuildInformationNode></Children></BuildInformationNode><BuildInformationNode Id="6ebc9247-c52a-4766-b053-fbcec64e9568" ParentId="84d0cec0-3977-4037-abf9-b5b92ef5fe3f" Type="ActivityTracking">
  <Fields>
    <InformationField Name="ActivityInstanceId" Value="16" />
    <InformationField Name="ActivityType" Value="If" />
    <InformationField Name="DisplayName" Value="If Build Reason is ValidateShelveset" />
    <InformationField Name="Duration" Value="00:00:00" />
    <InformationField Name="State" Value="Closed" />
    <InformationField Name="StartTime" Value="2014-05-26T14:21:37.9526350Z" />
    <InformationField Name="FinishTime" Value="2014-05-26T14:21:37.9526350Z" />
  </Fields>
<Children><BuildInformationNode Id="58d65580-1a2e-4946-9def-c1afa117516a" ParentId="6ebc9247-c52a-4766-b053-fbcec64e9568" Type="ActivityInput">
  <Fields>
    <InformationField Name="Condition" Value="False" />
  </Fields>
<Children /></BuildInformationNode></Children></BuildInformationNode></Children></BuildInformationNode><BuildInformationNode Id="d5df4670-924b-471a-a36c-a7a909aa347f" ParentId="0f43d437-d573-4d70-abd0-a597a361d63b" Type="AgentScopeActivityTracking">
  <Fields>
    <InformationField Name="ReservationStatus" Value="AgentReleased" />
    <InformationField Name="ReservedAgentUri" Value="vstfs:///Build/Agent/23" />
    <InformationField Name="ReservedAgentName" Value="Hosted Build Agent" />
    <InformationField Name="ActivityInstanceId" Value="17" />
    <InformationField Name="ActivityType" Value="AgentScope" />
    <InformationField Name="DisplayName" Value="Run On Agent" />
    <InformationField Name="Duration" Value="00:01:41" />
    <InformationField Name="State" Value="Closed" />
    <InformationField Name="StartTime" Value="2014-05-26T14:21:37.9636329Z" />
    <InformationField Name="FinishTime" Value="2014-05-26T14:23:19.2625864Z" />
    <InformationField Name="PossibleAgents" Value="vstfs:///Build/Agent/23=Hosted Build Agent" />
  </Fields>
<Children><BuildInformationNode Id="5d2227b5-7700-4b6a-8ac8-4dbd4d1969ac" ParentId="d5df4670-924b-471a-a36c-a7a909aa347f" Type="ActivityInput">
  <Fields>
    <InformationField Name="MaxWaitTime" Value="04:00:00" />
    <InformationField Name="MaxExecutionTime" Value="00:00:00" />
    <InformationField Name="ReservationSpec" Value="Name=*, Tags=" />
  </Fields>
<Children /></BuildInformationNode><BuildInformationNode Id="e7746df7-7b8a-4cb4-8e0f-2268a641275a" ParentId="d5df4670-924b-471a-a36c-a7a909aa347f" Type="ActivityOutput">
  <Fields>
    <InformationField Name="Result" Value="Hosted Build Agent (vstfs:///Build/Agent/23)" />
  </Fields>
<Children /></BuildInformationNode></Children></BuildInformationNode><BuildInformationNode Id="f70f606b-b83d-4da8-aa0a-2cdbc157d389" ParentId="0f43d437-d573-4d70-abd0-a597a361d63b" Type="BuildMessage">
  <Fields>
    <InformationField Name="Importance" Value="Normal" />
    <InformationField Name="Message" Value="Skipped execution of Check In Gated Changes because of BuildReason BatchedCI" />
    <InformationField Name="Timestamp" Value="2014-05-26T14:23:19.2785856Z" />
  </Fields>
<Children /></BuildInformationNode><BuildInformationNode Id="e21c24a5-91f8-4fd4-9a09-2e6b49e41cdf" ParentId="0f43d437-d573-4d70-abd0-a597a361d63b" Type="ActivityInput">
  <Fields>
    <InformationField Name="MSBuildMultiProc" Value="True" />
    <InformationField Name="Verbosity" Value="Normal" />
    <InformationField Name="CreateWorkItem" Value="True" />
    <InformationField Name="SourceAndSymbolServerSettings" Value="Index Sources" />
    <InformationField Name="RunCodeAnalysis" Value="AsConfigured" />
    <InformationField Name="SolutionSpecificBuildOutputs" Value="False" />
    <InformationField Name="TestSpecs" Value="Run tests in test sources matching **\*test*.dll, Target platform: 'X86'" />
    <InformationField Name="AgentSettings" Value="Use agent where Name=* and Tags is empty; Max Wait Time: 04:00:00" />
    <InformationField Name="MSBuildPlatform" Value="Auto" />
    <InformationField Name="PrivateDropLocation" />
    <InformationField Name="MSBuildArguments" />
    <InformationField Name="CreateLabel" Value="True" />
    <InformationField Name="AssociateChangesetsAndWorkItems" Value="True" />
    <InformationField Name="GetVersion" />
    <InformationField Name="CleanWorkspace" Value="All" />
    <InformationField Name="PerformTestImpactAnalysis" Value="True" />
    <InformationField Name="BuildSettings" Value="Build 1 project(s) for 1 platform(s) and configuration(s)" />
    <InformationField Name="BuildNumberFormat" Value="$(BuildDefinitionName)_$(Date:yyyyMMdd)$(Rev:.r)" />
    <InformationField Name="DisableTests" Value="False" />
  </Fields>
<Children /></BuildInformationNode></Children></BuildInformationNode>
</BuildInformation>